README
run_tests
setup.py
cxmanage.egg-info/PKG-INFO
cxmanage.egg-info/SOURCES.txt
cxmanage.egg-info/dependency_links.txt
cxmanage.egg-info/requires.txt
cxmanage.egg-info/top_level.txt
cxmanage_api/__init__.py
cxmanage_api/crc32.py
cxmanage_api/credentials.py
cxmanage_api/cx_exceptions.py
cxmanage_api/decorators.py
cxmanage_api/fabric.py
cxmanage_api/firmware_package.py
cxmanage_api/image.py
cxmanage_api/ip_retriever.py
cxmanage_api/loggers.py
cxmanage_api/node.py
cxmanage_api/simg.py
cxmanage_api/tasks.py
cxmanage_api/tftp.py
cxmanage_api/ubootenv.py
cxmanage_api/cli/__init__.py
cxmanage_api/cli/commands/__init__.py
cxmanage_api/cli/commands/config.py
cxmanage_api/cli/commands/eeprom.py
cxmanage_api/cli/commands/fabric.py
cxmanage_api/cli/commands/fw.py
cxmanage_api/cli/commands/info.py
cxmanage_api/cli/commands/ipdiscover.py
cxmanage_api/cli/commands/ipmitool.py
cxmanage_api/cli/commands/mc.py
cxmanage_api/cli/commands/power.py
cxmanage_api/cli/commands/sensor.py
cxmanage_api/cli/commands/tspackage.py
cxmanage_api/tests/__init__.py
cxmanage_api/tests/dummy.py
cxmanage_api/tests/dummy_bmc.py
cxmanage_api/tests/dummy_image.py
cxmanage_api/tests/dummy_ip_retriever.py
cxmanage_api/tests/dummy_node.py
cxmanage_api/tests/dummy_test.py
cxmanage_api/tests/dummy_ubootenv.py
cxmanage_api/tests/fabric_test.py
cxmanage_api/tests/image_test.py
cxmanage_api/tests/node_test.py
cxmanage_api/tests/tasks_test.py
cxmanage_api/tests/test_credentials.py
cxmanage_api/tests/tftp_test.py
cxmanage_api/tests/utilities.py
scripts/cxmanage
scripts/cxmux
scripts/sol_tabs