Metadata-Version: 1.1
Name: cxmanage
Version: 0.12.2
Summary: Calxeda Management Utility
Home-page: UNKNOWN
Author: george.kraft, Jason.Hobbs, sls.jarvis, SLS-BrianKe
Author-email: pkg-admin@silverlining-systems.com
License: UNKNOWN
Platform: UNKNOWN
Classifier: License :: OSI Approved :: BSD License
Classifier: Programming Language :: Python :: 2.7
